[
{"title":"The Sumerians","imageUrl":"https://m.media-amazon.com/images/I/81hdFIda+SL._AC_UF1000,1000_QL80_.jpg","price":"21","description":"Cradle of all Theism and Civilizations","id":"0.490795593259691"},
{"title": "Ancient Egypt","imageUrl": "https://m.media-amazon.com/images/I/91Jae26f4jL._AC_UF1000,1000_QL80_.jpg","price": "25","description": "A comprehensive guide to ancient Egyptian civilization","id": "0.123456789012345"},
{"title": "Greek Mythology","imageUrl": "https://cdn.kobo.com/book-images/c4665980-dd1a-40c4-a234-271bf9764ab1/1200/1200/False/greek-mythology-25.jpg","price": "18","description": "Explore the fascinating world of Greek gods and heroes","id": "0.987654321098765"}
]